mcp_pypi_qj001a/__init__.py
mcp_pypi_qj001a/py.typed
mcp_pypi_qj001a-0.1.2.dist-info/WHEEL
mcp_pypi_qj001a-0.1.2.dist-info/METADATA
mcp_pypi_qj001a-0.1.2.dist-info/RECORD
