Metadata-Version: 2.3
Name: mcp-pypi-qj001a
Version: 0.1.2
Summary: Add your description here
Author: qiao jian
Author-email: qiao jian <qj189@qq.com>
Requires-Dist: mcp[cli]>=1.12.2
Requires-Python: >=3.13
